easytrace/__init__.py
easytrace/trace.py
easytrace-0.0.2.dist-info/LICENSE
easytrace-0.0.2.dist-info/METADATA
easytrace-0.0.2.dist-info/WHEEL
easytrace-0.0.2.dist-info/top_level.txt
easytrace-0.0.2.dist-info/RECORD
