Metadata-Version: 2.1
Name: easytrace
Version: 0.0.2
Summary: A lightweight tracing library for python
Author-email: Aidan Ferguson <aidan.t.ferguson@gmail.com>
Project-URL: Homepage, https://github.com/pypa/sampleproject
Project-URL: Issues, https://github.com/pypa/sampleproject/issues
Classifier: Programming Language :: Python :: 3
Classifier: License :: OSI Approved :: MIT License
Classifier: Operating System :: OS Independent
Requires-Python: >=3.2
License-File: LICENSE
